{
  "connection": "default",
  "collectionName": "",
  "info": {
    "name": "product",
    "description": ""
  },
  "options": {
    "timestamps": true
  },
  "attributes": {
    "name": {
      "default": "",
      "type": "string"
    },
    "category": {
      "default": "",
      "type": "string"
    },
    "model": {
      "default": "",
      "type": "string"
    },
    "advantages": {
      "default": "",
      "type": "text"
    },
    "images": {
      "default": "",
      "type": "json"
    },
    "specs": {
      "default": "",
      "type": "json"
    },
    "features": {
      "default": "",
      "type": "json"
    },
    "spec sheet": {
      "default": "",
      "type": "string"
    }
  }
}